README.md
setup.cfg
setup.py
attention/__init__.py
attention/attention.py
decoder/__init__.py
decoder/decoder.py
decoder/decoder_layer.py
encoder/__init__.py
encoder/encoder.py
encoder/encoder_layer.py
evaluation/__init__.py
evaluation/evaluate.py
lr_scheduler/__init__.py
lr_scheduler/custom_scheduler.py
masker/__init__.py
masker/masker.py
positional_encoder/__init__.py
positional_encoder/positional_encoder.py
preprocessing/__init__.py
preprocessing/data_process.py
training/__init__.py
training/training.py
transformer/__init__.py
transformer/transformer.py
transformer_model.egg-info/PKG-INFO
transformer_model.egg-info/SOURCES.txt
transformer_model.egg-info/dependency_links.txt
transformer_model.egg-info/requires.txt
transformer_model.egg-info/top_level.txt