Metadata-Version: 1.2
Name: transformer-model
Version: 1.0.1
Summary: A Transformer model implementation in TensorFlow 2.0
Home-page: https://github.com/zbloss/TransformerModel
Author: Zachary Bloss
Author-email: zacharybloss@gmail.com
License: gpl-3.0
Download-URL: https://github.com/zbloss/TransformerModel/archive/v1.0.1.tar.gz
Keywords: Transformer,seq2seq,SelfAttention
Platform: UNKNOWN
Classifier: Development Status :: 5 - Production/Stable
Classifier: Intended Audience :: Developers
Classifier: Topic :: Software Development :: Build Tools
Classifier: License :: OSI Approved :: MIT License
Classifier: Programming Language :: Python :: 3
Requires-Python: >=3.5
